beancounttime/__init__.py
beancounttime/time.py
beancounttime-0.1.1.dist-info/LICENSE
beancounttime-0.1.1.dist-info/METADATA
beancounttime-0.1.1.dist-info/WHEEL
beancounttime-0.1.1.dist-info/top_level.txt
beancounttime-0.1.1.dist-info/RECORD
