Metadata-Version: 2.1
Name: beancounttime
Version: 0.1.1
Summary: Beancount time handling plugin
Home-page: https://vonshednob.cc/beancounttime
Author: vonshednob
Author-email: contact+beancounttime@vonshednob.cc
License: Copyright (c) 2021 Robert Labudda
Platform: UNKNOWN
Requires: beancount
Requires-Python: >=3.4
License-File: LICENSE
